freqgen/__init__.py
freqgen/__version__.py
freqgen/cli.py
freqgen/freqgen.py
freqgen/generate.py
freqgen/pyeasyga.py
freqgen/visualize.py
freqgen-0.1.0.dist-info/LICENSE
freqgen-0.1.0.dist-info/METADATA
freqgen-0.1.0.dist-info/PKG-INFO 2
freqgen-0.1.0.dist-info/SOURCES 2.txt
freqgen-0.1.0.dist-info/WHEEL
freqgen-0.1.0.dist-info/entry_points 2.txt
freqgen-0.1.0.dist-info/entry_points.txt
freqgen-0.1.0.dist-info/requires 2.txt
freqgen-0.1.0.dist-info/top_level.txt
freqgen-0.1.0.dist-info/RECORD
