Metadata-Version: 2.1
Name: freqgen
Version: 0.1.0
Summary: Generate DNA sequences with specified amino acid, codon, and k-mer frequencies.
Home-page: https://github.com/Lab41/freqgen
Author: Benjamin Lee
Author-email: benjamindlee@me.com
License: MIT
Platform: UNKNOWN
Classifier: License :: OSI Approved :: Apache Software License
Classifier: Programming Language :: Python
Classifier: Programming Language :: Python :: 3
Classifier: Programming Language :: Python :: 3.6
Classifier: Programming Language :: Python :: Implementation :: CPython
Classifier: Topic :: Scientific/Engineering :: Bio-Informatics
Requires-Python: >=3.5.0
Requires-Dist: numpy
Requires-Dist: click (<=6.7)
Requires-Dist: biopython
Requires-Dist: pyyaml
Requires-Dist: click-default-group
Requires-Dist: dit
Requires-Dist: bokeh
Requires-Dist: colorama
